sellium/__init__.py
sellium/_http.py
sellium/client.py
sellium/errors.py
sellium/types.py
sellium/services/__init__.py
sellium/services/blacklist.py
sellium/services/coupons.py
sellium/services/customers.py
sellium/services/feedback.py
sellium/services/groups.py
sellium/services/orders.py
sellium/services/products.py
sellium/services/store.py
sellium/services/tickets.py
sellium-0.1.0.dist-info/METADATA
sellium-0.1.0.dist-info/WHEEL
sellium-0.1.0.dist-info/top_level.txt
sellium-0.1.0.dist-info/RECORD
