Metadata-Version: 2.4
Name: sellium
Version: 0.1.0
Summary: Official Python SDK for the Sellium API.
Author: Sellium
License: MIT
Project-URL: Homepage, https://github.com/Sellium-site/sellium-python
Project-URL: Repository, https://github.com/Sellium-site/sellium-python
Requires-Python: >=3.9
Requires-Dist: httpx>=0.27.0
